TeleFlow/__init__.py
teleflow-0.2.0.dist-info/METADATA
teleflow-0.2.0.dist-info/WHEEL
teleflow-0.2.0.dist-info/top_level.txt
teleflow-0.2.0.dist-info/RECORD
